libs_n_utils_package_uq_2022/3class_ds_select_save.py
libs_n_utils_package_uq_2022/MI_feature_importance.py
libs_n_utils_package_uq_2022/RF_feature_importance.py
libs_n_utils_package_uq_2022/RF_feimp_weighted_average_wasserstein.py
libs_n_utils_package_uq_2022/UNSW_NB15_data_preparation.py
libs_n_utils_package_uq_2022/__init__.py
libs_n_utils_package_uq_2022/alternate_feature_wasserstein.py
libs_n_utils_package_uq_2022/attack_types.py
libs_n_utils_package_uq_2022/average_wasserstein.py
libs_n_utils_package_uq_2022/boruta_feature_selection.py
libs_n_utils_package_uq_2022/boruta_visualisation.py
libs_n_utils_package_uq_2022/combine_2feather.py
libs_n_utils_package_uq_2022/combine_2pickles.py
libs_n_utils_package_uq_2022/combine_3pickles.py
libs_n_utils_package_uq_2022/combine_folder_csv.py
libs_n_utils_package_uq_2022/compare_pickle_files_in_folder.py
libs_n_utils_package_uq_2022/config_template.py
libs_n_utils_package_uq_2022/csv_folder_to_feather_folder.py
libs_n_utils_package_uq_2022/csv_folder_to_pickle_folder.py
libs_n_utils_package_uq_2022/datasets_information.py
libs_n_utils_package_uq_2022/dict_manipulation.py
libs_n_utils_package_uq_2022/edit_CIC.py
libs_n_utils_package_uq_2022/edit_CIC_ton.py
libs_n_utils_package_uq_2022/feather_2m_sel_cols.py
libs_n_utils_package_uq_2022/feather_fldr_2_pickle_fldr.py
libs_n_utils_package_uq_2022/inter_dataset_feature_wasserstein.py
libs_n_utils_package_uq_2022/intra_dataset_feature_wasserstein.py
libs_n_utils_package_uq_2022/lib_NN_functional.py
libs_n_utils_package_uq_2022/lib_NN_models.py
libs_n_utils_package_uq_2022/lib_binary_classification.py
libs_n_utils_package_uq_2022/lib_data_preprocessing.py
libs_n_utils_package_uq_2022/lib_dataframe_manipulation.py
libs_n_utils_package_uq_2022/lib_embedding.py
libs_n_utils_package_uq_2022/lib_feature_calculation.py
libs_n_utils_package_uq_2022/lib_file_manipulation.py
libs_n_utils_package_uq_2022/lib_flow.py
libs_n_utils_package_uq_2022/lib_helpers.py
libs_n_utils_package_uq_2022-0.0.5.8.dist-info/METADATA
libs_n_utils_package_uq_2022-0.0.5.8.dist-info/WHEEL
libs_n_utils_package_uq_2022-0.0.5.8.dist-info/licenses/LICENSE
libs_n_utils_package_uq_2022-0.0.5.8.dist-info/RECORD
